lifepy/__init__.py
lifepy/lifepy.py
lifepy-1.0.6.dist-info/LICENSE
lifepy-1.0.6.dist-info/METADATA
lifepy-1.0.6.dist-info/WHEEL
lifepy-1.0.6.dist-info/top_level.txt
lifepy-1.0.6.dist-info/RECORD
