Metadata-Version: 2.1
Name: lifepy
Version: 1.0.6
Summary: A package made for simulating and visualizing Conways game of life instances
Home-page: https://github.com/Jael-G/lifepy
Author: Jael Gonzalez
Author-email: jael.gonzalez1@upr.edu
License: UNKNOWN
Platform: UNKNOWN
Classifier: Programming Language :: Python :: 3
Classifier: License :: OSI Approved :: MIT License
Classifier: Operating System :: OS Independent
Requires-Python: >=3.6
License-File: LICENSE
